ckanfetch-0.3-py2.7-nspkg.pth
ckanfetch/cli.py
ckanfetch-0.3.dist-info/LICENSE
ckanfetch-0.3.dist-info/METADATA
ckanfetch-0.3.dist-info/WHEEL
ckanfetch-0.3.dist-info/entry_points.txt
ckanfetch-0.3.dist-info/namespace_packages.txt
ckanfetch-0.3.dist-info/top_level.txt
ckanfetch-0.3.dist-info/RECORD
