Metadata-Version: 2.1
Name: ckanfetch
Version: 0.3
Summary: UNKNOWN
Home-page: https://github.com/fwoerister/ckan-dataset-fetcher
Author: Florian Woerister
Author-email: e1126205@student.tuwien.ac.at
License: GNU Affero General Public License v3.0
Platform: UNKNOWN
Requires-Dist: Click
